[
  {
    "index": 339,
    "coors": [
      [
        582,
        1516
      ],
      [
        1144,
        1006
      ]
    ]
  },
  {
    "index": 340,
    "coors": [
      [
        628,
        1494
      ],
      [
        1134,
        936
      ]
    ]
  },
  {
    "index": 341,
    "coors": [
      [
        668,
        1340
      ],
      [
        1138,
        826
      ]
    ]
  },
  {
    "index": 342,
    "coors": [
      [
        700,
        1248
      ],
      [
        1142,
        764
      ]
    ]
  },
  {
    "index": 343,
    "coors": [
      [
        736,
        1124
      ],
      [
        1148,
        680
      ]
    ]
  },
  {
    "index": 344,
    "coors": [
      [
        758,
        1038
      ],
      [
        1144,
        636
      ]
    ]
  },
  {
    "index": 345,
    "coors": [
      [
        788,
        944
      ],
      [
        1152,
        570
      ]
    ]
  },
  {
    "index": 346,
    "coors": [
      [
        808,
        882
      ],
      [
        1150,
        530
      ]
    ]
  },
  {
    "index": 347,
    "coors": [
      [
        834,
        820
      ],
      [
        1144,
        486
      ]
    ]
  },
  {
    "index": 348,
    "coors": [
      [
        848,
        760
      ],
      [
        1150,
        450
      ]
    ]
  },
  {
    "index": 349,
    "coors": [
      [
        870,
        700
      ],
      [
        1152,
        406
      ]
    ]
  },
  {
    "index": 350,
    "coors": [
      [
        882,
        666
      ],
      [
        1160,
        380
      ]
    ]
  },
  {
    "index": 351,
    "coors": [
      [
        904,
        612
      ],
      [
        1164,
        338
      ]
    ]
  },
  {
    "index": 352,
    "coors": [
      [
        908,
        564
      ],
      [
        1162,
        316
      ]
    ]
  },
  {
    "index": 353,
    "coors": [
      [
        928,
        522
      ],
      [
        1168,
        282
      ]
    ]
  },
  {
    "index": 354,
    "coors": [
      [
        938,
        496
      ],
      [
        1174,
        262
      ]
    ]
  },
  {
    "index": 355,
    "coors": [
      [
        954,
        446
      ],
      [
        1182,
        232
      ]
    ]
  },
  {
    "index": 356,
    "coors": [
      [
        960,
        428
      ],
      [
        1178,
        216
      ]
    ]
  },
  {
    "index": 357,
    "coors": [
      [
        970,
        392
      ],
      [
        1180,
        196
      ]
    ]
  },
  {
    "index": 358,
    "coors": [
      [
        980,
        380
      ],
      [
        1180,
        184
      ]
    ]
  },
  {
    "index": 359,
    "coors": [
      [
        990,
        358
      ],
      [
        1186,
        170
      ]
    ]
  },
  {
    "index": 360,
    "coors": [
      [
        1006,
        330
      ],
      [
        1184,
        152
      ]
    ]
  },
  {
    "index": 361,
    "coors": [
      [
        1016,
        312
      ],
      [
        1188,
        144
      ]
    ]
  },
  {
    "index": 362,
    "coors": [
      [
        1020,
        292
      ],
      [
        1192,
        130
      ]
    ]
  },
  {
    "index": 363,
    "coors": [
      [
        1036,
        274
      ],
      [
        1198,
        114
      ]
    ]
  },
  {
    "index": 364,
    "coors": [
      [
        1040,
        256
      ],
      [
        1200,
        102
      ]
    ]
  },
  {
    "index": 365,
    "coors": [
      [
        1052,
        238
      ],
      [
        1206,
        86
      ]
    ]
  },
  {
    "index": 366,
    "coors": [
      [
        1052,
        222
      ],
      [
        1214,
        76
      ]
    ]
  },
  {
    "index": 367,
    "coors": [
      [
        1062,
        208
      ],
      [
        1212,
        62
      ]
    ]
  },
  {
    "index": 368,
    "coors": [
      [
        1066,
        202
      ],
      [
        1214,
        56
      ]
    ]
  },
  {
    "index": 369,
    "coors": [
      [
        1076,
        180
      ],
      [
        1222,
        44
      ]
    ]
  },
  {
    "index": 370,
    "coors": [
      [
        1082,
        170
      ],
      [
        1220,
        38
      ]
    ]
  },
  {
    "index": 371,
    "coors": [
      [
        1092,
        148
      ],
      [
        1222,
        26
      ]
    ]
  },
  {
    "index": 372,
    "coors": [
      [
        1094,
        138
      ],
      [
        1226,
        18
      ]
    ]
  },
  {
    "index": 373,
    "coors": [
      [
        1096,
        126
      ],
      [
        1228,
        8
      ]
    ]
  },
  {
    "index": 374,
    "coors": [
      [
        1102,
        114
      ],
      [
        1230,
        2
      ]
    ]
  }
]